CHANGES.rst
MANIFEST.in
README.rst
requirements-dev.txt
requirements.txt
setup.py
apps/__init__.py
apps/sru_language_modeling.py
docs/Makefile
docs/conf.py
docs/index.rst
docs/make.bat
docs/_build/_static/fix_rtd.css
docs/_static/fix_rtd.css
docs/datatypes/queue.rst
docs/datatypes/stack.rst
docs/nlp/dependence.rst
docs/nlp/fjconvert.rst
docs/nlp/nertag.rst
docs/nlp/postag.rst
docs/nlp/segment.rst
docs/nlp/srl.rst
docs/nlp/stopwords.rst
docs/nn/keras_resnet.rst
docs/utils/common.rst
docs/utils/data.rst
docs/utils/file.rst
docs/utils/time.rst
oujago/__init__.py
oujago.egg-info/PKG-INFO
oujago.egg-info/SOURCES.txt
oujago.egg-info/dependency_links.txt
oujago.egg-info/requires.txt
oujago.egg-info/top_level.txt
oujago/datatypes/__init__.py
oujago/datatypes/queue.py
oujago/datatypes/stack.py
oujago/nlp/__init__.py
oujago/nlp/dependence.py
oujago/nlp/fjconvert.py
oujago/nlp/nertag.py
oujago/nlp/postag.py
oujago/nlp/sdp.py
oujago/nlp/segment.py
oujago/nlp/sentence_split.py
oujago/nlp/srl.py
oujago/nlp/stopwords.py
oujago/nn/__init__.py
oujago/nn/keras_inception.py
oujago/nn/keras_resnet.py
oujago/nn/tf_resnet.py
oujago/nn/torch_alexnet.py
oujago/nn/torch_densenet.py
oujago/nn/torch_inception.py
oujago/nn/torch_resnet.py
oujago/nn/torch_squeezenet.py
oujago/nn/torch_sru.py
oujago/nn/torch_vgg.py
oujago/utils/__init__.py
oujago/utils/common.py
oujago/utils/compression.py
oujago/utils/config.py
oujago/utils/data.py
oujago/utils/exception.py
oujago/utils/file.py
oujago/utils/time.py
tests/__init__.py
tests/algorithms/__init__.py
tests/algorithms/test_datatypes.py
tests/nlp/__init__.py
tests/nlp/test_pos.py
tests/nlp/test_seg.py
tests/nlp/test_stopwords.py
tests/nlp/test_utils.py
tests/nn/__init__.py
tests/others/test_common.py
tests/utils/__init__.py
tests/utils/test_common.py
tests/utils/test_data.py