Metadata-Version: 1.0
Name: oujago
Version: 0.1.14
Summary: Coding Makes Life Easier
Home-page: https://github.com/oujago/oujago
Author: Chao-Ming Wang
Author-email: oujago@gmail.com
License: UNKNOWN
Platform: UNKNOWN
